<VisioDocument xmlns="urn:schemas-microsoft-com:office:visio">
	<DocumentProperties>
		<Title>EMRG Index Page</Title>
		<HyperlinkBase href=""></HyperlinkBase>
	</DocumentProperties>
	<Pages>
		<Page ID="0" Name="nvis_index" NameU="technical_index">
			<Shapes>
				<Shape ID="20" UniqueID="{BC274856-64E2-4A42-9069-1F4AAE1536C2}" Name="Sheet.20" NameU="Sheet.20">
					<Text>Understanding The Testing Required
Setting up a station and making a few “local” contacts does not prove NVIS as an emergency communications solution. Many antennas will allow local contacts, but the operator has little control of who, when or where they can contact. The purpose of NVIS testing, is to learn how to contact specific stations at specific times.

From the testing, EMRG can develop an NVIS deployment plan which allows consistent, reliable communications, regardless of the location, time of day or time of year.</Text>
					<XForm>
						<PinX Unit="MM">5.807086614173227</PinX>
						<PinY Unit="MM">5.708661417322835</PinY>
					</XForm>
				</Shape>
				<Shape ID="17" UniqueID="{62950397-9AFF-4C26-BF01-7589EF31259B}" Name="Sheet.17" NameU="Sheet.17">
					<Text>There is small group within EMRG that have expressed an interest to work on testing NVIS as a solution for emergency communications in Ottawa. NVIS is not new (WWII), but there is not a great deal of concise information on applying NVIS. The purpose of the EMRG testing is to determine how to best use NVIS in this area, including antennas and frequencies to use.
If you are interested, send an email to VE3OCE@RAC.CA</Text>
					<XForm>
						<PinX Unit="MM">5.807086614173228</PinX>
						<PinY Unit="MM">7.165354330708661</PinY>
					</XForm>
				</Shape>
				<Shape ID="6" UniqueID="{2E3F8602-4303-44E3-BE84-EEA09FE1C181}" Name="Sheet.6" NameU="Sheet.6">
					<Text>NVIS INDEX</Text>
					<XForm>
						<PinX Unit="MM">4.980314960629921</PinX>
						<PinY Unit="MM">8.799212598425196</PinY>
					</XForm>
				</Shape>
				<Shape ID="4" UniqueID="{89D1ADA8-BCFB-4945-9637-53FA97FF64D2}" Name="Sheet.4" NameU="Sheet.4">
					<XForm>
						<PinX Unit="MM">4.980314960629920</PinX>
						<PinY Unit="MM">10.078740157480315</PinY>
					</XForm>
				</Shape>
				<Shape ID="1" UniqueID="{FF929D45-1E11-45B4-A8B5-59593009AEF1}" Name="Sheet.1" NameU="Sheet.1">
					<XForm>
						<PinX Unit="MM">1.306485126859141</PinX>
						<PinY Unit="MM">10.094662246736485</PinY>
					</XForm>
				</Shape>
				<Shape ID="2" UniqueID="{A2EE85CA-8E38-4007-A6BF-19E956E48C6E}" Name="Sheet.2" NameU="Sheet.2">
					<XForm>
						<PinX Unit="MM">8.917170698924732</PinX>
						<PinY Unit="MM">10.094652230971128</PinY>
					</XForm>
				</Shape>
				<Shape ID="3" UniqueID="{CEC43FF0-452F-40A3-9482-9CA75E8B0003}" Name="Sheet.3" NameU="Sheet.3">
					<Text>Emergency Measures Radio Group
Ottawa ARES
- Two Names, One Group, One Purpose -

Service de liaison radio en cas d'urgence</Text>
					<XForm>
						<PinX Unit="MM">5.157480314960630</PinX>
						<PinY Unit="MM">10.078740157480318</PinY>
					</XForm>
				</Shape>
				<Shape ID="5" UniqueID="{836A7884-760B-44CE-8490-94F2E9AA1A3F}" Name="Sheet.5" NameU="Sheet.5">
					<Text>Volunteer Emergency Radio Communications -Serving Ottawa Canada</Text>
					<XForm>
						<PinX Unit="MM">4.960629921259843</PinX>
						<PinY Unit="MM">9.194006999125110</PinY>
					</XForm>
					<Scratch>
						<B>
							<SolutionXML>
								<HLURL:Hyperlinks xmlns:HLURL="urn:schemas-microsoft-com:office:visio:dghlinkext">
									<HLURL:Hyperlink ID="1">
										<HLURL:Description>City of Ottawa Home Page</HLURL:Description>
										<HLURL:Address>http://www.ottawa.ca</HLURL:Address>
										<HLURL:SubAddress></HLURL:SubAddress>
										<HLURL:Default>0</HLURL:Default>
										<HLURL:AbsoluteURL>http://www.ottawa.ca</HLURL:AbsoluteURL>
									</HLURL:Hyperlink>
								</HLURL:Hyperlinks>
							</SolutionXML>
						</B>
					</Scratch>
				</Shape>
				<Shape ID="13" UniqueID="{E9324F95-5231-4E7D-9F6D-D30AFFB1EFA1}" Name="Sheet.13" NameU="Sheet.13">
					<XForm>
						<PinX Unit="MM">4.980314960629920</PinX>
						<PinY Unit="MM">7.735633748906388</PinY>
					</XForm>
				</Shape>
				<Shape ID="18" UniqueID="{044BF821-D8C2-4B52-9B47-C5DDC4030540}" Name="Sheet.18" NameU="Sheet.18">
					<Text>NVIS Introduction</Text>
					<XForm>
						<PinX Unit="MM">1.043307086614172</PinX>
						<PinY Unit="MM">7.452742782152232</PinY>
					</XForm>
					<Scratch>
						<B>
							<SolutionXML>
								<HLURL:Hyperlinks xmlns:HLURL="urn:schemas-microsoft-com:office:visio:dghlinkext">
									<HLURL:Hyperlink ID="1">
										<HLURL:Description>EMRG Introduction To NVIS</HLURL:Description>
										<HLURL:Address>http://www.emrg.ca/nvis/nvisintro.htm</HLURL:Address>
										<HLURL:SubAddress></HLURL:SubAddress>
										<HLURL:Default>0</HLURL:Default>
										<HLURL:AbsoluteURL>http://www.emrg.ca/nvis/nvisintro.htm</HLURL:AbsoluteURL>
									</HLURL:Hyperlink>
								</HLURL:Hyperlinks>
							</SolutionXML>
						</B>
					</Scratch>
				</Shape>
				<Shape ID="19" UniqueID="{294D63F6-E6B2-46B7-8C72-3DCD7537FF4C}" Name="Sheet.19" NameU="Sheet.19">
					<Text>NVIS TESTING</Text>
					<XForm>
						<PinX Unit="MM">1.043307086614174</PinX>
						<PinY Unit="MM">6.299212598425195</PinY>
					</XForm>
					<Scratch>
						<B>
							<SolutionXML>
								<HLURL:Hyperlinks xmlns:HLURL="urn:schemas-microsoft-com:office:visio:dghlinkext">
									<HLURL:Hyperlink ID="1">
										<HLURL:Description>EMRG NVIS Testing Information</HLURL:Description>
										<HLURL:Address>http://www.emrg.ca/nvis/nvistesting.htm</HLURL:Address>
										<HLURL:SubAddress></HLURL:SubAddress>
										<HLURL:Default>0</HLURL:Default>
										<HLURL:AbsoluteURL>http://www.emrg.ca/nvis/nvistesting.htm</HLURL:AbsoluteURL>
									</HLURL:Hyperlink>
								</HLURL:Hyperlinks>
							</SolutionXML>
						</B>
					</Scratch>
				</Shape>
				<Shape ID="25" UniqueID="{BDA31BCD-4D36-4F94-948D-B438003EF34B}" Name="Sheet.25" NameU="Sheet.25">
					<Text>EMRG NVIS</Text>
					<XForm>
						<PinX Unit="MM">1.043307086614174</PinX>
						<PinY Unit="MM">6.899606299212598</PinY>
					</XForm>
					<Scratch>
						<B>
							<SolutionXML>
								<HLURL:Hyperlinks xmlns:HLURL="urn:schemas-microsoft-com:office:visio:dghlinkext">
									<HLURL:Hyperlink ID="1">
										<HLURL:Description>EMRG Application of NVIS In Ottawa</HLURL:Description>
										<HLURL:Address>http://www.emrg.ca/nvis/emrg_nvis.htm</HLURL:Address>
										<HLURL:SubAddress></HLURL:SubAddress>
										<HLURL:Default>0</HLURL:Default>
										<HLURL:AbsoluteURL>http://www.emrg.ca/nvis/emrg_nvis.htm</HLURL:AbsoluteURL>
									</HLURL:Hyperlink>
								</HLURL:Hyperlinks>
							</SolutionXML>
						</B>
					</Scratch>
				</Shape>
				<Shape ID="29" UniqueID="{7FE57EA2-25F4-4ABB-8405-4216B99F1A5B}" Name="Sheet.29" NameU="Sheet.29">
					<Text>NVIS provides a solution for situations where there is no repeater or repeaters have failed, and simplex VHF/UHF communications cannot link the two locations that need to communicate. </Text>
					<XForm>
						<PinX Unit="MM">4.980314960629920</PinX>
						<PinY Unit="MM">4.064113079615048</PinY>
					</XForm>
				</Shape>
				<Shape ID="15" UniqueID="{08CCAA73-C4B0-48DF-957D-2157E6F94A53}" Name="Sheet.15" NameU="Sheet.15">
					<XForm>
						<PinX Unit="MM">5.807086614173227</PinX>
						<PinY Unit="MM">6.303123359580052</PinY>
					</XForm>
				</Shape>
				<Shape ID="16" UniqueID="{FF575DFB-4644-455D-A707-CEC095295A0B}" Name="Sheet.16" NameU="Sheet.16">
					<XForm>
						<PinX Unit="MM">9.645669291338582</PinX>
						<PinY Unit="MM">6.294128390201227</PinY>
					</XForm>
				</Shape>
				<Shape ID="35" UniqueID="{44602790-2911-40D3-A7E9-568087815D45}" Name="Question mark" NameU="Question mark" Master="4">
					<XForm>
						<PinX Unit="MM">4.330708661417321</PinX>
						<PinY Unit="MM">3.519877515310585</PinY>
					</XForm>
				</Shape>
				<Shape ID="36" UniqueID="{9ABAA5EE-3C6D-44D0-8375-288217343B54}" Name="Sheet.36" NameU="Sheet.36">
					<Text>
					</Text>
					<XForm>
						<PinX Unit="MM">0.098425196850394</PinX>
						<PinY Unit="MM">0.147637795275591</PinY>
					</XForm>
				</Shape>
				<Shape ID="38" UniqueID="{651E8477-65B9-4A13-92B8-11BEFC2C22C6}" Name="Sheet.38" NameU="Sheet.38">
					<Text>VE3OCE@RAC.CA</Text>
					<XForm>
						<PinX Unit="MM">5.243657042869639</PinX>
						<PinY Unit="MM">3.430201224846893</PinY>
					</XForm>
				</Shape>
				<Shape ID="9" UniqueID="{60889204-D145-4645-B898-3AF3E82EA314}" Name="Sheet.9" NameU="Sheet.9">
					<XForm>
						<PinX Unit="MM">1.316876640419946</PinX>
						<PinY Unit="MM">3.456679790026247</PinY>
					</XForm>
					<Scratch>
						<B>
							<SolutionXML>
								<HLURL:Hyperlinks xmlns:HLURL="urn:schemas-microsoft-com:office:visio:dghlinkext">
									<HLURL:Hyperlink ID="1">
										<HLURL:Description>EMRG Home Page</HLURL:Description>
										<HLURL:Address>http://www.emrg.ca</HLURL:Address>
										<HLURL:SubAddress></HLURL:SubAddress>
										<HLURL:Default>0</HLURL:Default>
										<HLURL:AbsoluteURL>http://www.emrg.ca</HLURL:AbsoluteURL>
									</HLURL:Hyperlink>
								</HLURL:Hyperlinks>
							</SolutionXML>
						</B>
					</Scratch>
				</Shape>
				<Shape ID="11" UniqueID="{C1AF326E-2C7D-42E8-9DC5-F5DBA99DE208}" Name="Sheet.11" NameU="Sheet.11">
					<Text>HOME</Text>
					<XForm>
						<PinX Unit="MM">0.988293963254593</PinX>
						<PinY Unit="MM">0.214881889763779</PinY>
					</XForm>
				</Shape>
				<Shape ID="41" UniqueID="{2AB7AD9E-2535-46DA-BDF2-029E4CDDAAA8}" Name="Sheet.41" NameU="Sheet.41">
					<Text>Near Vertical Incident Skywave (NVIS) transmits radio signals almost straight up (80 to 90 degrees), where it is reflected back down to the receiving station. This achieves dependable local area High Frequency (HF) communications within an area with a radius up to about 500 kilometres using frequencies between 2 and 10 or 12 Megahertz. </Text>
					<XForm>
						<PinX Unit="MM">4.980314960629921</PinX>
						<PinY Unit="MM">8.139763779527559</PinY>
					</XForm>
				</Shape>
				<Shape ID="8" UniqueID="{C356598E-9E60-4482-9421-D5BC399BD562}" Name="Sheet.8" NameU="Sheet.8">
					<Text>NVIS Web Links</Text>
					<XForm>
						<PinX Unit="MM">1.043307086614174</PinX>
						<PinY Unit="MM">5.185052493438320</PinY>
					</XForm>
					<Scratch>
						<B>
							<SolutionXML>
								<HLURL:Hyperlinks xmlns:HLURL="urn:schemas-microsoft-com:office:visio:dghlinkext">
									<HLURL:Hyperlink ID="1">
										<HLURL:Description>EMRG NVIS Web Links</HLURL:Description>
										<HLURL:Address>http://www.emrg.ca/nvis/nvislinks.htm</HLURL:Address>
										<HLURL:SubAddress></HLURL:SubAddress>
										<HLURL:Default>0</HLURL:Default>
										<HLURL:AbsoluteURL>http://www.emrg.ca/nvis/nvislinks.htm</HLURL:AbsoluteURL>
									</HLURL:Hyperlink>
								</HLURL:Hyperlinks>
							</SolutionXML>
						</B>
					</Scratch>
				</Shape>
				<Shape ID="7" UniqueID="{464CA0A3-3B5E-4207-B626-41DB91CC4BE8}" Name="Sheet.7" NameU="Sheet.7">
					<Text>NVIS Antennas</Text>
					<XForm>
						<PinX Unit="MM">1.043307086614174</PinX>
						<PinY Unit="MM">5.708661417322834</PinY>
					</XForm>
					<Scratch>
						<B>
							<SolutionXML>
								<HLURL:Hyperlinks xmlns:HLURL="urn:schemas-microsoft-com:office:visio:dghlinkext">
									<HLURL:Hyperlink ID="1">
										<HLURL:Description>EMRG NVIS Antenna Information</HLURL:Description>
										<HLURL:Address>http://www.emrg.ca/nvis/nvisantennas.htm</HLURL:Address>
										<HLURL:SubAddress></HLURL:SubAddress>
										<HLURL:Default>0</HLURL:Default>
										<HLURL:AbsoluteURL>http://www.emrg.ca/nvis/nvisantennas.htm</HLURL:AbsoluteURL>
									</HLURL:Hyperlink>
								</HLURL:Hyperlinks>
							</SolutionXML>
						</B>
					</Scratch>
				</Shape>
				<Shape ID="12" UniqueID="{33145525-511F-46C8-97EB-5BE5D48A06E9}" Name="Sheet.12" NameU="Sheet.12">
					<Text>RAC HF Propagation Forecast</Text>
					<XForm>
						<PinX Unit="MM">7.608267716535432</PinX>
						<PinY Unit="MM">4.594501312335958</PinY>
					</XForm>
					<Scratch>
						<B>
							<SolutionXML>
								<HLURL:Hyperlinks xmlns:HLURL="urn:schemas-microsoft-com:office:visio:dghlinkext">
									<HLURL:Hyperlink ID="1">
										<HLURL:Description>RAC HF Propagation Forecasts</HLURL:Description>
										<HLURL:Address>http://www.rac.ca/opsinfo/propagationa.htm</HLURL:Address>
										<HLURL:SubAddress></HLURL:SubAddress>
										<HLURL:Default>0</HLURL:Default>
										<HLURL:AbsoluteURL>http://www.rac.ca/opsinfo/propagationa.htm</HLURL:AbsoluteURL>
									</HLURL:Hyperlink>
								</HLURL:Hyperlinks>
							</SolutionXML>
						</B>
					</Scratch>
				</Shape>
				<Shape ID="14" UniqueID="{910FD83A-FE07-48BF-9AD7-11E9FC24A23D}" Name="Sheet.14" NameU="Sheet.14">
					<Text>NVIS Optimum Frequency Maps</Text>
					<XForm>
						<PinX Unit="MM">3.853346456692914</PinX>
						<PinY Unit="MM">4.594501312335958</PinY>
					</XForm>
					<Scratch>
						<B>
							<SolutionXML>
								<HLURL:Hyperlinks xmlns:HLURL="urn:schemas-microsoft-com:office:visio:dghlinkext">
									<HLURL:Hyperlink ID="1">
										<HLURL:Description>HF Pack Maps for optimum NVIS Frequency</HLURL:Description>
										<HLURL:Address>http://www.hfpack.com/</HLURL:Address>
										<HLURL:SubAddress></HLURL:SubAddress>
										<HLURL:Default>0</HLURL:Default>
										<HLURL:AbsoluteURL>http://www.hfpack.com/</HLURL:AbsoluteURL>
									</HLURL:Hyperlink>
								</HLURL:Hyperlinks>
							</SolutionXML>
						</B>
					</Scratch>
				</Shape>
			</Shapes>
		</Page>
	</Pages>
</VisioDocument>
